bibliometrics/__init__.py
bibliometrics/__main__.py
bibliometrics/bibliometrics.py
bibliometrics/calculator.py
bibliometrics/text_length.py
bibliometrics-4.0.0.dist-info/METADATA
bibliometrics-4.0.0.dist-info/WHEEL
bibliometrics-4.0.0.dist-info/licenses/LICENSE
bibliometrics-4.0.0.dist-info/RECORD
