Metadata-Version: 2.4
Name: bibliometrics
Version: 4.0.0
Summary: Summarize your Google Scholar bibliometrics in an SVG
Project-URL: GitHub Repository, https://github.com/cicirello/bibliometrics
Project-URL: Bug Tracker, https://github.com/cicirello/bibliometrics/issues
Project-URL: Changelog, https://github.com/cicirello/bibliometrics/blob/main/CHANGELOG.md
Author-email: "Vincent A. Cicirello" <development@cicirello.org>
License-File: LICENSE
Keywords: Hirsch index,SVG,SVG generation,a-index,bibliometrics,e-index,g-index,h-index,h-median,i10-index,i100-index,i1000-index,i10000-index,journals,m-quotient,o-index,publications,r-index,researcher,scholar,scientometrics,w-index
Classifier: Intended Audience :: Education
Classifier: Intended Audience :: Science/Research
Classifier: License :: OSI Approved :: MIT License
Classifier: Operating System :: OS Independent
Classifier: Programming Language :: Python :: 3
Classifier: Topic :: Multimedia :: Graphics
Classifier: Topic :: Other/Nonlisted Topic
Requires-Python: >=3.10
